{
  "project_info": {
    "project_number": "901909518862",
    "project_id": "sw2-project-9bc47",
    "storage_bucket": "sw2-project-9bc47.appspot.com"
  },
  "client": [
    {
      "client_info": {
        "mobilesdk_app_id": "1:901909518862:android:ec3ccbbc460d264a123a5f",
        "android_client_info": {
          "package_name": "com.example.amazona"
        }
      },
      "oauth_client": [],
      "api_key": [
        {
          "current_key": "AIzaSyDdK6fObxQD7Zn1CUvIX1aR_AJZeYgKnuI"
        }
      ],
      "services": {
        "appinvite_service": {
          "other_platform_oauth_client": []
        }
      }
    }
  ],
  "configuration_version": "1"
}